rmlab_http_client/__init__.py
rmlab_http_client/cache.py
rmlab_http_client/types.py
rmlab_http_client/client/__init__.py
rmlab_http_client/client/_core.py
rmlab_http_client/client/async_ctx.py
rmlab_http_client/client/sync_ctx.py
tests/__init__.py
tests/async_test.py
tests/payloads_test.py
tests/sync_test.py
tests/types_test.py
rmlab_http_client-0.4.0.dist-info/LICENSE
rmlab_http_client-0.4.0.dist-info/METADATA
rmlab_http_client-0.4.0.dist-info/WHEEL
rmlab_http_client-0.4.0.dist-info/top_level.txt
rmlab_http_client-0.4.0.dist-info/RECORD
