Metadata-Version: 2.1
Name: rmlab-http-client
Version: 0.4.0
Summary: RMLab module wrapping a HTTP client providing auth and async utilities.
Home-page: https://github.com/antonrv/rmlab-py-http-client
Author: Anton Rey
Author-email: aanton.rv@gmail.com
Project-URL: Bug Tracker, https://github.com/antonrv/rmlab-py-http-client/issues
Classifier: License :: OSI Approved :: MIT License
Classifier: Development Status :: 4 - Beta
Classifier: Programming Language :: Python
Classifier: Programming Language :: Python :: 3.11
Classifier: Programming Language :: Python :: 3 :: Only
Classifier: Operating System :: OS Independent
Classifier: Environment :: Console
Classifier: Intended Audience :: Developers
Classifier: Topic :: Office/Business
Classifier: Topic :: Scientific/Engineering
Classifier: Topic :: Software Development :: User Interfaces
Classifier: Framework :: AsyncIO
Requires-Python: >=3.11
License-File: LICENSE
Requires-Dist: aiodns (==3.0.0)
Requires-Dist: aiohttp (==3.8.4)
Requires-Dist: Brotli (==1.0.9)
Requires-Dist: rmlab-errors (==0.1.6)
